mo_sqlite/__init__.py
mo_sqlite/database.py
mo_sqlite/jx_to_sql.py
mo_sqlite/sql_script.py
mo_sqlite/transacfion.py
mo_sqlite/types.py
mo_sqlite/utils.py
mo_sqlite/expressions/__init__.py
mo_sqlite/expressions/_utils.py
mo_sqlite/expressions/sql_add_op.py
mo_sqlite/expressions/sql_alias_op.py
mo_sqlite/expressions/sql_and_op.py
mo_sqlite/expressions/sql_case_op.py
mo_sqlite/expressions/sql_cast_op.py
mo_sqlite/expressions/sql_coalesce_op.py
mo_sqlite/expressions/sql_concat_op.py
mo_sqlite/expressions/sql_eq_op.py
mo_sqlite/expressions/sql_group_by_op.py
mo_sqlite/expressions/sql_gt_op.py
mo_sqlite/expressions/sql_gte_op.py
mo_sqlite/expressions/sql_in_op.py
mo_sqlite/expressions/sql_inner_join_op.py
mo_sqlite/expressions/sql_instr_op.py
mo_sqlite/expressions/sql_is_null_op.py
mo_sqlite/expressions/sql_limit_op.py
mo_sqlite/expressions/sql_literal.py
mo_sqlite/expressions/sql_lt_op.py
mo_sqlite/expressions/sql_lte_op.py
mo_sqlite/expressions/sql_not_op.py
mo_sqlite/expressions/sql_or_op.py
mo_sqlite/expressions/sql_order_by_op.py
mo_sqlite/expressions/sql_script.py
mo_sqlite/expressions/sql_select_op.py
mo_sqlite/expressions/sql_substr_op.py
mo_sqlite/expressions/sql_variable.py
mo_sqlite-2.673.25037.dist-info/LICENSE
mo_sqlite-2.673.25037.dist-info/METADATA
mo_sqlite-2.673.25037.dist-info/WHEEL
mo_sqlite-2.673.25037.dist-info/top_level.txt
mo_sqlite-2.673.25037.dist-info/RECORD
